README.rst
flask_aggregator.py
setup.py
Flask_Aggregator.egg-info/PKG-INFO
Flask_Aggregator.egg-info/SOURCES.txt
Flask_Aggregator.egg-info/dependency_links.txt
Flask_Aggregator.egg-info/not-zip-safe
Flask_Aggregator.egg-info/requires.txt
Flask_Aggregator.egg-info/top_level.txt