Metadata-Version: 1.1
Name: Flask-Aggregator
Version: 0.1.2
Summary: Batch the GET requests to your REST API into a single POST
Home-page: https://github.com/ramnes/flask-aggregator
Author: Guillaume Gelin
Author-email: contact@ramnes.eu
License: MIT
Platform: any
Classifier: Environment :: Web Environment
Classifier: Intended Audience :: Developers
Classifier: Operating System :: OS Independent
Classifier: Programming Language :: Python
Classifier: Topic :: Internet :: WWW/HTTP :: Dynamic Content
Classifier: Topic :: Software Development :: Libraries :: Python Modules
